README.md
setup.py
SCOT_bio.egg-info/PKG-INFO
SCOT_bio.egg-info/SOURCES.txt
SCOT_bio.egg-info/dependency_links.txt
SCOT_bio.egg-info/requires.txt
SCOT_bio.egg-info/top_level.txt
scot/__init__.py
scot/multi_omics_model.py
scot/tensorsc_model.py